pacs_q-1.2.6.dist-info/licenses/LICENSE
pacsq_toolkit/__init__.py
pacsq_toolkit/file_find.py
pacsq_toolkit/openmm_engine.py
pacsq_toolkit/pacs_q.py
pacsq_toolkit/pacs_q_md.py
pacsq_toolkit/pacsana_dis_collection.py
pacsq_toolkit/pacsana_dis_collection_mpi.py
pacsq_toolkit/pacsana_procupine.py
pacsq_toolkit/pacsana_traj2g16.py
pacsq_toolkit/pacsana_traj2orca.py
pacsq_toolkit/pacsq_cuda_run.py
pacsq_toolkit/pacsq_exq_run.py
pacsq_toolkit/pacsq_openmm_rerun.py
pacsq_toolkit/pacsq_openmm_run.py
pacsq_toolkit/pacsq_pmemd_rerun.py
pacsq_toolkit/pacsq_pmemd_run.py
pacsq_toolkit/pacsq_rerun.py
pacsq_toolkit/pacsq_run.py
pacsq_toolkit/pacsrmsd.py
pacsq_toolkit/pmemd_run.py
pacsq_toolkit/qmmm_setting.py
pacsq_toolkit/sander_run.py
pacsq_toolkit/sander_run_mpi.py
pacsq_toolkit/test_json.py
pacs_q-1.2.6.dist-info/METADATA
pacs_q-1.2.6.dist-info/WHEEL
pacs_q-1.2.6.dist-info/entry_points.txt
pacs_q-1.2.6.dist-info/top_level.txt
pacs_q-1.2.6.dist-info/RECORD
