Metadata-Version: 2.4
Name: PaCS-Q
Version: 1.2.6
Summary: PaCS-Q is a Python toolkit designed to assist with Parallel Cascade Selection simulations (PaCS) for studying protein structural transitions in MD and QM/MM MD level.
Author-email: Lian Duan <duanlian0810@gmail.com>
License-Expression: MIT
Project-URL: Homepage, https://https://github.com/nyelidl/PaCS-Q
Classifier: Programming Language :: Python :: 3
Classifier: Operating System :: OS Independent
Requires-Python: >=3.9
License-File: LICENSE
Requires-Dist: MDAnalysis>=2.9.0
Requires-Dist: numpy<2.3
Requires-Dist: parmed>=4.3.0
Requires-Dist: netCDF4
Requires-Dist: cftime
Dynamic: license-file
